package_parser/__init__.py
package_parser/__meta__.py
package_parser/utils.py
package_parser/__pycache__/__init__.cpython-36.pyc
package_parser/__pycache__/__init__.cpython-38.pyc
package_parser/__pycache__/__meta__.cpython-36.pyc
package_parser/__pycache__/__meta__.cpython-38.pyc
package_parser/__pycache__/utils.cpython-36.pyc
package_parser/__pycache__/utils.cpython-38.pyc
package_parser-1.0.2.dist-info/LICENSE
package_parser-1.0.2.dist-info/METADATA
package_parser-1.0.2.dist-info/WHEEL
package_parser-1.0.2.dist-info/top_level.txt
package_parser-1.0.2.dist-info/RECORD
