Metadata-Version: 2.1
Name: package-parser
Version: 1.0.2
Summary: Python utility to parse package filenames to get the name and version of the package.
Home-page: https://github.com/justengel/package_parser
Author: Justin Engel
Author-email: jtengel08@gmail.com
License: MIT
Download-URL: https://github.com/justengel/package_parser/archive/v1.0.2.tar.gz
Keywords: python package name version
Platform: any
Classifier: Programming Language :: Python
Classifier: Programming Language :: Python :: 3
Classifier: Operating System :: OS Independent
Requires-Dist: packaging (>=20.3)
